i3blocks_spotify_persist.py
i3blocks_spotify_persist-1.2.0.dist-info/LICENSE
i3blocks_spotify_persist-1.2.0.dist-info/METADATA
i3blocks_spotify_persist-1.2.0.dist-info/WHEEL
i3blocks_spotify_persist-1.2.0.dist-info/entry_points.txt
i3blocks_spotify_persist-1.2.0.dist-info/top_level.txt
i3blocks_spotify_persist-1.2.0.dist-info/zip-safe
i3blocks_spotify_persist-1.2.0.dist-info/RECORD
