Metadata-Version: 2.1
Name: i3blocks-spotify-persist
Version: 1.2.0
Summary: A persistent i3blocks blocklet for the Spotify desktop app
Home-page: https://github.com/un-def/i3blocks-spotify-persist
Author: un.def
Author-email: me@undef.im
License: MIT
Platform: UNKNOWN
Classifier: Development Status :: 5 - Production/Stable
Classifier: Intended Audience :: End Users/Desktop
Classifier: License :: OSI Approved :: MIT License
Classifier: Operating System :: POSIX :: Linux
Classifier: Programming Language :: Python :: 3
Classifier: Programming Language :: Python :: 3.5
Classifier: Programming Language :: Python :: 3.6
Classifier: Programming Language :: Python :: 3.7
Classifier: Programming Language :: Python :: 3.8
Requires-Python: >=3.5
Requires-Dist: dbus-python (<1.3,>=1.2.4)
Requires-Dist: PyGObject (<3.37,>=3.26)
